LICENSE.txt
MANIFEST.in
README
bootstrap.py
buildout.cfg
setup.py
src/django_pressroom.egg-info/PKG-INFO
src/django_pressroom.egg-info/SOURCES.txt
src/django_pressroom.egg-info/dependency_links.txt
src/django_pressroom.egg-info/requires.txt
src/django_pressroom.egg-info/top_level.txt
src/pressroom/__init__.py
src/pressroom/admin.py
src/pressroom/feeds.py
src/pressroom/models.py
src/pressroom/testsettings.py
src/pressroom/urls.py
src/pressroom/views.py
src/pressroom/migrations/0001_initial.py
src/pressroom/migrations/0002_add_enable_comments.py
src/pressroom/migrations/__init__.py
src/pressroom/templates/feeds/rss_description.html
src/pressroom/templates/feeds/rss_title.html
src/pressroom/templates/pressroom/article_archive.html
src/pressroom/templates/pressroom/article_archive_day.html
src/pressroom/templates/pressroom/article_archive_month.html
src/pressroom/templates/pressroom/article_archive_year.html
src/pressroom/templates/pressroom/article_detail.html
src/pressroom/templates/pressroom/article_list.html
src/pressroom/templates/pressroom/index.html
src/pressroom/templates/pressroom/view_section.html
src/pressroom/tests/__init__.py
src/pressroom/tests/test_articles.py
src/pressroom/tests/urls.py
src/pressroom/tests/templates/base.html
src/pressroom/tests/templates/base_site.html