Metadata-Version: 1.0
Name: django-pressroom
Version: 0.6
Summary: A pressroom application for django.
Home-page: http://code.google.com/p/django-pressroom/
Author: Justin Driscoll, Michael Thornhill
Author-email: michael@maithu.com
License: BSD
Platform: UNKNOWN
Classifier: Development Status :: 4 - Beta
Classifier: Framework :: Django
Classifier: Intended Audience :: Developers
Classifier: License :: OSI Approved :: BSD License
Classifier: Operating System :: OS Independent
Classifier: Programming Language :: Python
Classifier: Topic :: Internet :: WWW/HTTP
